{
  "ticks": {
    "27-05-2026": [
      {
        "time": "16:00:00",
        "ltp": 76115.95
      },
      {
        "time": "11:53:00",
        "ltp": 76097.25
      },
      {
        "time": "12:02:00",
        "ltp": 76065.2
      },
      {
        "time": "14:00:00",
        "ltp": 75980
      },
      {
        "time": "16:00:00",
        "ltp": 75863.15
      }
    ],
    "25-06-2026": [
      {
        "time": "16:00:00",
        "ltp": 76498.6
      },
      {
        "time": "11:53:00",
        "ltp": 76510
      },
      {
        "time": "12:02:00",
        "ltp": 76480
      },
      {
        "time": "14:00:00",
        "ltp": 76405
      },
      {
        "time": "16:00:00",
        "ltp": 76450
      },
      {
        "time": "09:53:00",
        "ltp": 76404.35
      },
      {
        "time": "13:54:00",
        "ltp": 75900
      },
      {
        "time": "16:00:00",
        "ltp": 75514.15
      },
      {
        "time": "12:03:00",
        "ltp": 75023
      },
      {
        "time": "16:00:00",
        "ltp": 74741.75
      },
      {
        "time": "11:54:00",
        "ltp": 74517.55
      },
      {
        "time": "16:00:00",
        "ltp": 75243.1
      },
      {
        "time": "12:45:00",
        "ltp": 74520
      },
      {
        "time": "16:00:00",
        "ltp": 74808.25
      },
      {
        "time": "10:55:00",
        "ltp": 74690
      },
      {
        "time": "14:42:00",
        "ltp": 74750
      },
      {
        "time": "16:00:00",
        "ltp": 74815
      },
      {
        "time": "11:51:00",
        "ltp": 74741.85
      },
      {
        "time": "15:31:00",
        "ltp": 74491.9
      },
      {
        "time": "16:00:00",
        "ltp": 74491.9
      },
      {
        "time": "12:25:00",
        "ltp": 74050
      },
      {
        "time": "16:00:00",
        "ltp": 73700
      },
      {
        "time": "09:30:00",
        "ltp": 74053.2
      },
      {
        "time": "13:28:00",
        "ltp": 73950
      },
      {
        "time": "16:00:00",
        "ltp": 74300
      },
      {
        "time": "10:12:00",
        "ltp": 74490
      },
      {
        "time": "14:08:00",
        "ltp": 74550.7
      },
      {
        "time": "16:00:00",
        "ltp": 74105
      },
      {
        "time": "11:52:00",
        "ltp": 74307.15
      },
      {
        "time": "16:00:00",
        "ltp": 74053.3
      },
      {
        "time": "10:31:00",
        "ltp": 74660.85
      },
      {
        "time": "14:38:00",
        "ltp": 75374.9
      },
      {
        "time": "16:00:00",
        "ltp": 75721.65
      },
      {
        "time": "12:33:00",
        "ltp": 76462.45
      },
      {
        "time": "16:00:00",
        "ltp": 76398.05
      },
      {
        "time": "13:08:00",
        "ltp": 76609.35
      },
      {
        "time": "16:00:00",
        "ltp": 76846.45
      },
      {
        "time": "10:38:00",
        "ltp": 77128
      },
      {
        "time": "15:31:00",
        "ltp": 77177.65
      },
      {
        "time": "16:00:00",
        "ltp": 77177.65
      },
      {
        "time": "11:57:00",
        "ltp": 77030
      },
      {
        "time": "16:00:00",
        "ltp": 77571.35
      },
      {
        "time": "10:49:00",
        "ltp": 76770.35
      },
      {
        "time": "15:26:00",
        "ltp": 76994.9
      },
      {
        "time": "16:00:00",
        "ltp": 76993
      },
      {
        "time": "11:07:00",
        "ltp": 77295
      },
      {
        "time": "16:00:00",
        "ltp": 77170.1
      },
      {
        "time": "11:15:00",
        "ltp": 77200
      },
      {
        "time": "14:20:00",
        "ltp": 76501.4
      },
      {
        "time": "16:00:00",
        "ltp": 76191.1
      },
      {
        "time": "11:16:00",
        "ltp": 76859.85
      },
      {
        "time": "14:16:00",
        "ltp": 77101
      },
      {
        "time": "16:00:00",
        "ltp": 77100
      },
      {
        "time": "10:08:00",
        "ltp": 77497.75
      },
      {
        "time": "13:32:00",
        "ltp": 77508.4
      },
      {
        "time": "16:00:00",
        "ltp": 77120
      }
    ],
    "30-07-2026": [
      {
        "time": "09:53:00",
        "ltp": 77039.75
      },
      {
        "time": "13:54:00",
        "ltp": 76500
      },
      {
        "time": "16:00:00",
        "ltp": 76242.75
      },
      {
        "time": "12:03:00",
        "ltp": 75600
      },
      {
        "time": "16:00:00",
        "ltp": 75296.1
      },
      {
        "time": "11:54:00",
        "ltp": 75094.25
      },
      {
        "time": "16:00:00",
        "ltp": 75774.5
      },
      {
        "time": "12:45:00",
        "ltp": 75003.1
      },
      {
        "time": "16:00:00",
        "ltp": 75215.35
      },
      {
        "time": "10:55:00",
        "ltp": 75135.35
      },
      {
        "time": "14:42:00",
        "ltp": 75260
      },
      {
        "time": "16:00:00",
        "ltp": 75300
      },
      {
        "time": "11:51:00",
        "ltp": 75175
      },
      {
        "time": "15:31:00",
        "ltp": 75050
      },
      {
        "time": "16:00:00",
        "ltp": 75050
      },
      {
        "time": "12:25:00",
        "ltp": 74501.35
      },
      {
        "time": "16:00:00",
        "ltp": 74173.05
      },
      {
        "time": "09:30:00",
        "ltp": 74518.15
      },
      {
        "time": "13:28:00",
        "ltp": 74422
      },
      {
        "time": "16:00:00",
        "ltp": 74751.85
      },
      {
        "time": "10:12:00",
        "ltp": 74885.6
      },
      {
        "time": "14:08:00",
        "ltp": 74959.95
      },
      {
        "time": "16:00:00",
        "ltp": 74548.45
      },
      {
        "time": "11:52:00",
        "ltp": 74750
      },
      {
        "time": "16:00:00",
        "ltp": 74500
      },
      {
        "time": "10:31:00",
        "ltp": 75084
      },
      {
        "time": "14:38:00",
        "ltp": 75840
      },
      {
        "time": "16:00:00",
        "ltp": 76220
      },
      {
        "time": "12:33:00",
        "ltp": 76975.5
      },
      {
        "time": "16:00:00",
        "ltp": 76939.8
      },
      {
        "time": "13:08:00",
        "ltp": 77129.95
      },
      {
        "time": "16:00:00",
        "ltp": 77369.35
      },
      {
        "time": "10:38:00",
        "ltp": 77592.75
      },
      {
        "time": "15:31:00",
        "ltp": 77638.8
      },
      {
        "time": "16:00:00",
        "ltp": 77638.8
      },
      {
        "time": "11:57:00",
        "ltp": 77499.9
      },
      {
        "time": "16:00:00",
        "ltp": 78000
      },
      {
        "time": "10:49:00",
        "ltp": 77265
      },
      {
        "time": "15:26:00",
        "ltp": 77440
      },
      {
        "time": "16:00:00",
        "ltp": 77439.4
      },
      {
        "time": "11:07:00",
        "ltp": 77777
      },
      {
        "time": "16:00:00",
        "ltp": 77706.65
      },
      {
        "time": "11:15:00",
        "ltp": 77670
      },
      {
        "time": "14:20:00",
        "ltp": 77043.65
      },
      {
        "time": "16:00:00",
        "ltp": 76750
      },
      {
        "time": "11:16:00",
        "ltp": 77440
      },
      {
        "time": "14:16:00",
        "ltp": 77691.55
      },
      {
        "time": "16:00:00",
        "ltp": 77679
      },
      {
        "time": "10:08:00",
        "ltp": 77995.4
      },
      {
        "time": "13:32:00",
        "ltp": 77995
      },
      {
        "time": "16:00:00",
        "ltp": 77706.85
      },
      {
        "time": "12:28:00",
        "ltp": 77262.6
      },
      {
        "time": "16:00:00",
        "ltp": 77221
      },
      {
        "time": "11:40:00",
        "ltp": 77200
      }
    ],
    "27-08-2026": [
      {
        "time": "10:49:00",
        "ltp": 77800
      },
      {
        "time": "15:26:00",
        "ltp": 77973.1
      },
      {
        "time": "16:00:00",
        "ltp": 77973.1
      },
      {
        "time": "11:07:00",
        "ltp": 78218.35
      },
      {
        "time": "16:00:00",
        "ltp": 78159.45
      },
      {
        "time": "11:15:00",
        "ltp": 78150
      },
      {
        "time": "14:20:00",
        "ltp": 77646.4
      },
      {
        "time": "16:00:00",
        "ltp": 77200
      },
      {
        "time": "11:16:00",
        "ltp": 77860
      },
      {
        "time": "14:16:00",
        "ltp": 78050
      },
      {
        "time": "16:00:00",
        "ltp": 78074.75
      },
      {
        "time": "10:08:00",
        "ltp": 78472
      },
      {
        "time": "13:32:00",
        "ltp": 78426.05
      },
      {
        "time": "16:00:00",
        "ltp": 78180
      },
      {
        "time": "12:28:00",
        "ltp": 77801.1
      },
      {
        "time": "16:00:00",
        "ltp": 77715.5
      },
      {
        "time": "11:40:00",
        "ltp": 77700
      }
    ],
    "24-09-2026": [
      {
        "time": "12:28:00",
        "ltp": 78117.9
      },
      {
        "time": "16:00:00",
        "ltp": 78110
      },
      {
        "time": "11:40:00",
        "ltp": 78110
      }
    ]
  }
}